relatable/__init__.py
relatable/relational_schema.py
relatable/table.py
relatable/tabulator.py
relatable-0.4.1.dist-info/LICENSE
relatable-0.4.1.dist-info/METADATA
relatable-0.4.1.dist-info/WHEEL
relatable-0.4.1.dist-info/top_level.txt
relatable-0.4.1.dist-info/RECORD
