Metadata-Version: 2.1
Name: relatable
Version: 0.4.1
Summary: Document-oriented to relational data conversion
Author-email: "Alexander M. Giordano" <am.giordano.carmena@gmail.com>
License: Copyright (c) 2018 The Python Packaging Authority        
Project-URL: Homepage, https://github.com/am-giordano/relatable
Classifier: Programming Language :: Python :: 3
Classifier: License :: OSI Approved :: MIT License
Classifier: Operating System :: OS Independent
Requires-Python: >=3.8
License-File: LICENSE
